{
  "laps": [
    {
      "meeting_key": 1271,
      "session_key": 9888,
      "driver_number": 4,
      "lap_number": 1,
      "date_start": null,
      "duration_sector_1": null,
      "duration_sector_2": 40.436,
      "duration_sector_3": 33.432,
      "i1_speed": 207,
      "i2_speed": 178,
      "is_pit_out_lap": false,
      "lap_duration": null,
      "segments_sector_1": [
        2048,
        2049,
        2049,
        2049,
        2049,
        2049
      ],
      "segments_sector_2": [
        2049,
        2049,
        2051,
        2049,
        2049,
        2049,
        2049,
        2049
      ],
      "segments_sector_3": [
        2049,
        2049,
        2051,
        2049,
        2049,
        2049,
        2049,
        2049
      ],
      "st_speed": 303
    },
    {
      "meeting_key": 1271,
      "session_key": 9888,
      "driver_number": 4,
      "lap_number": 2,
      "date_start": "2025-10-19T19:05:22.670000+00:00",
      "duration_sector_1": 27.278,
      "duration_sector_2": 39.909,
      "duration_sector_3": 33.463,
      "i1_speed": 213,
      "i2_speed": 178,
      "is_pit_out_lap": false,
      "lap_duration": 100.65,
      "segments_sector_1": [
        2049,
        2049,
        2049,
        2049,
        2049,
        2049
      ],
      "segments_sector_2": [
        2049,
        2049,
        2048,
        2049,
        2049,
        2049,
        2049,
        2048
      ],
      "segments_sector_3": [
        2049,
        2048,
        2051,
        2049,
        2048,
        2049,
        2048,
        2048
      ],
      "st_speed": 316
    },
    {
      "meeting_key": 1271,
      "session_key": 9888,
      "driver_number": 4,
      "lap_number": 3,
      "date_start": "2025-10-19T19:07:03.338000+00:00",
      "duration_sector_1": 27.004,
      "duration_sector_2": 39.508,
      "duration_sector_3": 34.001,
      "i1_speed": 217,
      "i2_speed": 180,
      "is_pit_out_lap": false,
      "lap_duration": 100.513,
      "segments_sector_1": [
        null,
        2049,
        2048,
        2049,
        2049,
        2049
      ],
      "segments_sector_2": [
        2051,
        2049,
        2051,
        2049,
        2049,
        2049,
        2049,
        2049
      ],
      "segments_sector_3": [
        2048,
        2048,
        2048,
        2048,
        2048,
        2048,
        2048,
        2048
      ],
      "st_speed": 330
    },
    {
      "meeting_key": 1271,
      "session_key": 9888,
      "driver_number": 4,
      "lap_number": 4,
      "date_start": "2025-10-19T19:08:43.937000+00:00",
      "duration_sector_1": 27.044,
      "duration_sector_2": 39.456,
      "duration_sector_3": 33.949,
      "i1_speed": 218,
      "i2_speed": 177,
      "is_pit_out_lap": false,
      "lap_duration": 100.449,
      "segments_sector_1": [
        null,
        2049,
        2048,
        2048,
        2049,
        2049
      ],
      "segments_sector_2": [
        2051,
        2049,
        2051,
        2049,
        2049,
        2048,
        2049,
        2049
      ],
      "segments_sector_3": [
        2048,
        2048,
        2048,
        2049,
        2048,
        2048,
        2049,
        2049
      ],
      "st_speed": 333
    },
    {
      "meeting_key": 1271,
      "session_key": 9888,
      "driver_number": 4,
      "lap_number": 5,
      "date_start": "2025-10-19T19:10:24.375000+00:00",
      "duration_sector_1": 27.003,
      "duration_sector_2": 39.575,
      "duration_sector_3": 33.81,
      "i1_speed": 219,
      "i2_speed": 175,
      "is_pit_out_lap": false,
      "lap_duration": 100.388,
      "segments_sector_1": [
        null,
        2049,
        2048,
        2048,
        2048,
        2049
      ],
      "segments_sector_2": [
        2049,
        2048,
        2051,
        2048,
        2048,
        2048,
        2048,
        2048
      ],
      "segments_sector_3": [
        2048,
        2048,
        2048,
        2048,
        2049,
        2049,
        2048,
        2048
      ],
      "st_speed": 329
    },
    {
      "meeting_key": 1271,
      "session_key": 9888,
      "driver_number": 4,
      "lap_number": 6,
      "date_start": "2025-10-19T19:12:04.670000+00:00",
      "duration_sector_1": 27.164,
      "duration_sector_2": 39.9,
      "duration_sector_3": 33.696,
      "i1_speed": 214,
      "i2_speed": 179,
      "is_pit_out_lap": false,
      "lap_duration": 100.76,
      "segments_sector_1": [
        2048,
        2048,
        2048,
        2051,
        2049,
        2048
      ],
      "segments_sector_2": [
        2048,
        2049,
        2048,
        2048,
        2048,
        2048,
        2048,
        2049
      ],
      "segments_sector_3": [
        2048,
        2048,
        2048,
        2048,
        2048,
        2048,
        2048,
        2048
      ],
      "st_speed": 308
    },
    {
      "meeting_key": 1271,
      "session_key": 9888,
      "driver_number": 4,
      "lap_number": 7,
      "date_start": "2025-10-19T19:13:45.544000+00:00",
      "duration_sector_1": 27.208,
      "duration_sector_2": 48.092,
      "duration_sector_3": 48.163,
      "i1_speed": null,
      "i2_speed": 147,
      "is_pit_out_lap": false,
      "lap_duration": 123.463,
      "segments_sector_1": [
        null,
        2048,
        2048,
        2048,
        2049,
        2048
      ],
      "segments_sector_2": [
        2048,
        2049,
        2048,
        2048,
        2048,
        2048,
        2048,
        2048
      ],
      "segments_sector_3": [
        2048,
        2048,
        2048,
        2048,
        2048,
        2048,
        2048,
        2048
      ],
      "st_speed": 215
    },
    {
      "meeting_key": 1271,
      "session_key": 9888,
      "driver_number": 4,
      "lap_number": 8,
      "date_start": "2025-10-19T19:15:48.911000+00:00",
      "duration_sector_1": 35.413,
      "duration_sector_2": 54.105,
      "duration_sector_3": 45.508,
      "i1_speed": 161,
      "i2_speed": 114,
      "is_pit_out_lap": false,
      "lap_duration": 135.026,
      "segments_sector_1": [
        null,
        2048,
        2048,
        2048,
        2048,
        2048
      ],
      "segments_sector_2": [
        2048,
        2048,
        2048,
        2048,
        2048,
        2048,
        2048,
        2048
      ],
      "segments_sector_3": [
        2048,
        2048,
        2048,
        2048,
        2048,
        2048,
        2048,
        2048
      ],
      "st_speed": 233
    },
    {
      "meeting_key": 1271,
      "session_key": 9888,
      "driver_number": 4,
      "lap_number": 9,
      "date_start": "2025-10-19T19:18:04.018000+00:00",
      "duration_sector_1": 29.137,
      "duration_sector_2": 39.543,
      "duration_sector_3": 32.969,
      "i1_speed": 210,
      "i2_speed": 180,
      "is_pit_out_lap": false,
      "lap_duration": 101.649,
      "segments_sector_1": [
        null,
        2048,
        2049,
        2048,
        2049,
        2048
      ],
      "segments_sector_2": [
        2048,
        2048,
        2048,
        2049,
        2048,
        2048,
        2048,
        2049
      ],
      "segments_sector_3": [
        2049,
        2049,
        2048,
        2049,
        2049,
        2049,
        2048,
        2048
      ],
      "st_speed": 308
    },
    {
      "meeting_key": 1271,
      "session_key": 9888,
      "driver_number": 4,
      "lap_number": 10,
      "date_start": "2025-10-19T19:19:45.612000+00:00",
      "duration_sector_1": 26.744,
      "duration_sector_2": 39.43,
      "duration_sector_3": 33.159,
      "i1_speed": 217,
      "i2_speed": 181,
      "is_pit_out_lap": false,
      "lap_duration": 99.333,
      "segments_sector_1": [
        null,
        2048,
        2051,
        2048,
        2049,
        2048
      ],
      "segments_sector_2": [
        2049,
        2049,
        2048,
        2048,
        2048,
        2048,
        2048,
        2049
      ],
      "segments_sector_3": [
        2048,
        2048,
        2048,
        2048,
        2048,
        2048,
        2048,
        2048
      ],
      "st_speed": 309
    },
    {
      "meeting_key": 1271,
      "session_key": 9888,
      "driver_number": 4,
      "lap_number": 11,
      "date_start": "2025-10-19T19:21:25.019000+00:00",
      "duration_sector_1": 26.796,
      "duration_sector_2": 39.699,
      "duration_sector_3": 33.2,
      "i1_speed": 216,
      "i2_speed": 178,
      "is_pit_out_lap": false,
      "lap_duration": 99.695,
      "segments_sector_1": [
        null,
        2048,
        2048,
        2048,
        2049,
        2048
      ],
      "segments_sector_2": [
        2048,
        2048,
        2048,
        2048,
        2048,
        2048,
        2048,
        2048
      ],
      "segments_sector_3": [
        2048,
        2048,
        2048,
        2049,
        2048,
        2048,
        2048,
        2048
      ],
      "st_speed": 308
    },
    {
      "meeting_key": 1271,
      "session_key": 9888,
      "driver_number": 4,
      "lap_number": 12,
      "date_start": "2025-10-19T19:23:04.647000+00:00",
      "duration_sector_1": 26.732,
      "duration_sector_2": 39.767,
      "duration_sector_3": 33.276,
      "i1_speed": 219,
      "i2_speed": 180,
      "is_pit_out_lap": false,
      "lap_duration": 99.775,
      "segments_sector_1": [
        null,
        2048,
        2048,
        2048,
        2049,
        2049
      ],
      "segments_sector_2": [
        2048,
        2048,
        2048,
        2048,
        2048,
        2048,
        2048,
        2048
      ],
      "segments_sector_3": [
        2048,
        2048,
        2048,
        2049,
        2048,
        2048,
        2048,
        2048
      ],
      "st_speed": 308
    },
    {
      "meeting_key": 1271,
      "session_key": 9888,
      "driver_number": 4,
      "lap_number": 13,
      "date_start": "2025-10-19T19:24:44.496000+00:00",
      "duration_sector_1": 26.651,
      "duration_sector_2": 39.637,
      "duration_sector_3": 33.424,
      "i1_speed": 221,
      "i2_speed": 179,
      "is_pit_out_lap": false,
      "lap_duration": 99.712,
      "segments_sector_1": [
        null,
        2048,
        2048,
        2048,
        2049,
        2049
      ],
      "segments_sector_2": [
        2048,
        2048,
        2048,
        2048,
        2048,
        2048,
        2048,
        2048
      ],
      "segments_sector_3": [
        2048,
        2048,
        2048,
        2049,
        2048,
        2048,
        2048,
        2048
      ],
      "st_speed": 311
    },
    {
      "meeting_key": 1271,
      "session_key": 9888,
      "driver_number": 4,
      "lap_number": 14,
      "date_start": "2025-10-19T19:26:24.219000+00:00",
      "duration_sector_1": 26.513,
      "duration_sector_2": 39.659,
      "duration_sector_3": 33.713,
      "i1_speed": 219,
      "i2_speed": 178,
      "is_pit_out_lap": false,
      "lap_duration": 99.885,
      "segments_sector_1": [
        2049,
        2049,
        2048,
        2048,
        2049,
        2048
      ],
      "segments_sector_2": [
        2048,
        2048,
        2048,
        2048,
        2048,
        2048,
        2048,
        2048
      ],
      "segments_sector_3": [
        2048,
        2048,
        2049,
        2048,
        2048,
        2048,
        2048,
        2048
      ],
      "st_speed": 328
    },
    {
      "meeting_key": 1271,
      "session_key": 9888,
      "driver_number": 4,
      "lap_number": 15,
      "date_start": "2025-10-19T19:28:04.034000+00:00",
      "duration_sector_1": 26.6,
      "duration_sector_2": 40.131,
      "duration_sector_3": 34.535,
      "i1_speed": 218,
      "i2_speed": 178,
      "is_pit_out_lap": false,
      "lap_duration": 101.266,
      "segments_sector_1": [
        null,
        2048,
        2048,
        2048,
        2048,
        2048
      ],
      "segments_sector_2": [
        2048,
        2048,
        2048,
        2048,
        2048,
        2048,
        2048,
        2048
      ],
      "segments_sector_3": [
        2048,
        2048,
        2048,
        2048,
        2048,
        2048,
        2048,
        2048
      ],
      "st_speed": 329
    },
    {
      "meeting_key": 1271,
      "session_key": 9888,
      "driver_number": 4,
      "lap_number": 16,
      "date_start": "2025-10-19T19:29:45.315000+00:00",
      "duration_sector_1": 26.673,
      "duration_sector_2": 40.382,
      "duration_sector_3": 33.571,
      "i1_speed": 216,
      "i2_speed": 178,
      "is_pit_out_lap": false,
      "lap_duration": 100.626,
      "segments_sector_1": [
        2048,
        2048,
        2048,
        2048,
        2048,
        2048
      ],
      "segments_sector_2": [
        2048,
        2048,
        2048,
        2048,
        2048,
        2048,
        2048,
        2048
      ],
      "segments_sector_3": [
        2048,
        2048,
        2048,
        2049,
        2048,
        2048,
        2048,
        2048
      ],
      "st_speed": 322
    },
    {
      "meeting_key": 1271,
      "session_key": 9888,
      "driver_number": 4,
      "lap_number": 17,
      "date_start": "2025-10-19T19:31:25.982000+00:00",
      "duration_sector_1": 26.392,
      "duration_sector_2": 39.817,
      "duration_sector_3": 33.696,
      "i1_speed": 215,
      "i2_speed": 180,
      "is_pit_out_lap": false,
      "lap_duration": 99.905,
      "segments_sector_1": [
        null,
        2048,
        2048,
        2048,
        2049,
        2049
      ],
      "segments_sector_2": [
        2048,
        2048,
        2051,
        2048,
        2048,
        2048,
        2048,
        2048
      ],
      "segments_sector_3": [
        2048,
        2048,
        2048,
        2049,
        2048,
        2048,
        2048,
        2048
      ],
      "st_speed": 322
    },
    {
      "meeting_key": 1271,
      "session_key": 9888,
      "driver_number": 4,
      "lap_number": 18,
      "date_start": "2025-10-19T19:33:05.835000+00:00",
      "duration_sector_1": 26.579,
      "duration_sector_2": 39.834,
      "duration_sector_3": 33.674,
      "i1_speed": null,
      "i2_speed": 180,
      "is_pit_out_lap": false,
      "lap_duration": 100.087,
      "segments_sector_1": [
        2049,
        2048,
        2048,
        2048,
        2048,
        2048
      ],
      "segments_sector_2": [
        2048,
        2048,
        2048,
        2048,
        2048,
        2049,
        2049,
        2048
      ],
      "segments_sector_3": [
        2048,
        2048,
        2048,
        2048,
        2048,
        2048,
        2048,
        2048
      ],
      "st_speed": 324
    },
    {
      "meeting_key": 1271,
      "session_key": 9888,
      "driver_number": 4,
      "lap_number": 19,
      "date_start": "2025-10-19T19:34:46.045000+00:00",
      "duration_sector_1": 26.397,
      "duration_sector_2": 39.796,
      "duration_sector_3": 34.41,
      "i1_speed": 220,
      "i2_speed": 180,
      "is_pit_out_lap": false,
      "lap_duration": 100.603,
      "segments_sector_1": [
        null,
        2049,
        2048,
        2048,
        2048,
        2048
      ],
      "segments_sector_2": [
        2048,
        2048,
        2049,
        2048,
        2048,
        2049,
        2049,
        2048
      ],
      "segments_sector_3": [
        2048,
        2048,
        2048,
        2048,
        2048,
        2048,
        2048,
        2048
      ],
      "st_speed": 333
    },
    {
      "meeting_key": 1271,
      "session_key": 9888,
      "driver_number": 4,
      "lap_number": 20,
      "date_start": "2025-10-19T19:36:26.491000+00:00",
      "duration_sector_1": 26.513,
      "duration_sector_2": 39.755,
      "duration_sector_3": 33.793,
      "i1_speed": 219,
      "i2_speed": 179,
      "is_pit_out_lap": false,
      "lap_duration": 100.061,
      "segments_sector_1": [
        2048,
        2048,
        2048,
        2048,
        2048,
        2048
      ],
      "segments_sector_2": [
        2048,
        2048,
        2048,
        2048,
        2048,
        2048,
        2048,
        2048
      ],
      "segments_sector_3": [
        2048,
        2048,
        2049,
        2048,
        2048,
        2048,
        2048,
        2048
      ],
      "st_speed": 330
    },
    {
      "meeting_key": 1271,
      "session_key": 9888,
      "driver_number": 4,
      "lap_number": 21,
      "date_start": "2025-10-19T19:38:06.676000+00:00",
      "duration_sector_1": 26.404,
      "duration_sector_2": 39.952,
      "duration_sector_3": 33.726,
      "i1_speed": 216,
      "i2_speed": 175,
      "is_pit_out_lap": false,
      "lap_duration": 100.082,
      "segments_sector_1": [
        2049,
        2048,
        2048,
        2049,
        2048,
        2049
      ],
      "segments_sector_2": [
        2048,
        2048,
        2048,
        2048,
        2048,
        2048,
        2048,
        2048
      ],
      "segments_sector_3": [
        2048,
        2048,
        2048,
        2049,
        2048,
        2048,
        2048
      ],
      "st_speed": 330
    },
    {
      "meeting_key": 1271,
      "session_key": 9888,
      "driver_number": 4,
      "lap_number": 22,
      "date_start": "2025-10-19T19:39:46.565000+00:00",
      "duration_sector_1": 26.708,
      "duration_sector_2": 40.068,
      "duration_sector_3": 33.213,
      "i1_speed": 224,
      "i2_speed": 179,
      "is_pit_out_lap": false,
      "lap_duration": 99.989,
      "segments_sector_1": [
        2048,
        2048,
        2048,
        2048,
        2048,
        2049
      ],
      "segments_sector_2": [
        2048,
        2048,
        2048,
        2048,
        2048,
        2048,
        2048,
        2048
      ],
      "segments_sector_3": [
        2048,
        2048,
        2048,
        2049,
        2049,
        2048,
        2048,
        2048
      ],
      "st_speed": 305
    },
    {
      "meeting_key": 1271,
      "session_key": 9888,
      "driver_number": 4,
      "lap_number": 23,
      "date_start": "2025-10-19T19:41:26.737000+00:00",
      "duration_sector_1": 26.444,
      "duration_sector_2": 39.865,
      "duration_sector_3": 33.027,
      "i1_speed": 227,
      "i2_speed": 183,
      "is_pit_out_lap": false,
      "lap_duration": 99.336,
      "segments_sector_1": [
        null,
        2048,
        2048,
        2048,
        2048,
        2049
      ],
      "segments_sector_2": [
        2048,
        2048,
        2048,
        2048,
        2048,
        2048,
        2048,
        2048
      ],
      "segments_sector_3": [
        2048,
        2048,
        2048,
        2049,
        2049,
        2048,
        2048,
        2048
      ],
      "st_speed": 306
    },
    {
      "meeting_key": 1271,
      "session_key": 9888,
      "driver_number": 4,
      "lap_number": 24,
      "date_start": "2025-10-19T19:43:06.046000+00:00",
      "duration_sector_1": 26.453,
      "duration_sector_2": 40.116,
      "duration_sector_3": 33.17,
      "i1_speed": 223,
      "i2_speed": 182,
      "is_pit_out_lap": false,
      "lap_duration": 99.739,
      "segments_sector_1": [
        null,
        2048,
        2048,
        2048,
        2049,
        2048
      ],
      "segments_sector_2": [
        2048,
        2048,
        2048,
        2048,
        2048,
        2048,
        2048,
        2048
      ],
      "segments_sector_3": [
        2048,
        2048,
        2048,
        2048,
        2048,
        2048,
        2048,
        2048
      ],
      "st_speed": 305
    },
    {
      "meeting_key": 1271,
      "session_key": 9888,
      "driver_number": 4,
      "lap_number": 25,
      "date_start": "2025-10-19T19:44:45.777000+00:00",
      "duration_sector_1": 26.434,
      "duration_sector_2": 39.787,
      "duration_sector_3": 33.335,
      "i1_speed": 224,
      "i2_speed": 182,
      "is_pit_out_lap": false,
      "lap_duration": 99.556,
      "segments_sector_1": [
        null,
        2048,
        2048,
        2048,
        2048,
        2048
      ],
      "segments_sector_2": [
        2048,
        2048,
        2048,
        2048,
        2048,
        2048,
        2048,
        2048
      ],
      "segments_sector_3": [
        2048,
        2048,
        2048,
        2048,
        2048,
        2048,
        2048,
        2048
      ],
      "st_speed": 306
    },
    {
      "meeting_key": 1271,
      "session_key": 9888,
      "driver_number": 4,
      "lap_number": 26,
      "date_start": "2025-10-19T19:46:25.355000+00:00",
      "duration_sector_1": 26.423,
      "duration_sector_2": 40.061,
      "duration_sector_3": 33.418,
      "i1_speed": 226,
      "i2_speed": 183,
      "is_pit_out_lap": false,
      "lap_duration": 99.902,
      "segments_sector_1": [
        null,
        2048,
        2048,
        2048,
        2048,
        2048
      ],
      "segments_sector_2": [
        2048,
        2048,
        2048,
        2048,
        2048,
        2048,
        2048,
        2048
      ],
      "segments_sector_3": [
        2048,
        2048,
        2048,
        2048,
        2048,
        2048,
        2048,
        2048
      ],
      "st_speed": 302
    },
    {
      "meeting_key": 1271,
      "session_key": 9888,
      "driver_number": 4,
      "lap_number": 27,
      "date_start": "2025-10-19T19:48:05.224000+00:00",
      "duration_sector_1": 26.36,
      "duration_sector_2": 40.066,
      "duration_sector_3": 33.358,
      "i1_speed": 225,
      "i2_speed": 183,
      "is_pit_out_lap": false,
      "lap_duration": 99.784,
      "segments_sector_1": [
        null,
        2048,
        2048,
        2048,
        2048,
        2049
      ],
      "segments_sector_2": [
        2048,
        2048,
        2048,
        2048,
        2048,
        2048,
        2048,
        2048
      ],
      "segments_sector_3": [
        2048,
        2048,
        2048,
        2048,
        2048,
        2048,
        2048,
        2048
      ],
      "st_speed": 304
    },
    {
      "meeting_key": 1271,
      "session_key": 9888,
      "driver_number": 4,
      "lap_number": 28,
      "date_start": "2025-10-19T19:49:45.036000+00:00",
      "duration_sector_1": 26.466,
      "duration_sector_2": 40.02,
      "duration_sector_3": 33.171,
      "i1_speed": 223,
      "i2_speed": 182,
      "is_pit_out_lap": false,
      "lap_duration": 99.657,
      "segments_sector_1": [
        null,
        2048,
        2048,
        2048,
        2048,
        2048
      ],
      "segments_sector_2": [
        2048,
        2048,
        2048,
        2048,
        2048,
        2048,
        2048,
        2048
      ],
      "segments_sector_3": [
        2048,
        2048,
        2048,
        2049,
        2048,
        2048,
        2048,
        2048
      ],
      "st_speed": 304
    },
    {
      "meeting_key": 1271,
      "session_key": 9888,
      "driver_number": 4,
      "lap_number": 29,
      "date_start": "2025-10-19T19:51:24.679000+00:00",
      "duration_sector_1": 26.451,
      "duration_sector_2": 39.943,
      "duration_sector_3": 33.155,
      "i1_speed": 224,
      "i2_speed": 181,
      "is_pit_out_lap": false,
      "lap_duration": 99.549,
      "segments_sector_1": [
        null,
        2048,
        2048,
        2048,
        2048,
        2048
      ],
      "segments_sector_2": [
        2048,
        2048,
        2048,
        2048,
        2048,
        2048,
        2048,
        2048
      ],
      "segments_sector_3": [
        2048,
        2048,
        2048,
        2048,
        2049,
        2048,
        2048,
        2048
      ],
      "st_speed": 304
    },
    {
      "meeting_key": 1271,
      "session_key": 9888,
      "driver_number": 4,
      "lap_number": 30,
      "date_start": "2025-10-19T19:53:04.171000+00:00",
      "duration_sector_1": 26.37,
      "duration_sector_2": 40.027,
      "duration_sector_3": 33.227,
      "i1_speed": 225,
      "i2_speed": 182,
      "is_pit_out_lap": false,
      "lap_duration": 99.624,
      "segments_sector_1": [
        null,
        2048,
        2048,
        2048,
        2049,
        2049
      ],
      "segments_sector_2": [
        2048,
        2048,
        2048,
        2048,
        2048,
        2048,
        2048,
        2048
      ],
      "segments_sector_3": [
        2048,
        2048,
        2048,
        2048,
        2049,
        2048,
        2048,
        2048
      ],
      "st_speed": 306
    },
    {
      "meeting_key": 1271,
      "session_key": 9888,
      "driver_number": 4,
      "lap_number": 31,
      "date_start": "2025-10-19T19:54:43.795000+00:00",
      "duration_sector_1": 26.379,
      "duration_sector_2": 40.188,
      "duration_sector_3": 33.554,
      "i1_speed": null,
      "i2_speed": 178,
      "is_pit_out_lap": false,
      "lap_duration": 100.121,
      "segments_sector_1": [
        null,
        2048,
        2048,
        2048,
        2048,
        2048
      ],
      "segments_sector_2": [
        2048,
        2048,
        2048,
        2048,
        2048,
        2048,
        2048,
        2048
      ],
      "segments_sector_3": [
        2048,
        2048,
        2048,
        2048,
        2048,
        2048,
        2048,
        2048
      ],
      "st_speed": 306
    },
    {
      "meeting_key": 1271,
      "session_key": 9888,
      "driver_number": 4,
      "lap_number": 32,
      "date_start": "2025-10-19T19:56:24.001000+00:00",
      "duration_sector_1": 26.44,
      "duration_sector_2": 40.957,
      "duration_sector_3": 34.33,
      "i1_speed": 227,
      "i2_speed": 183,
      "is_pit_out_lap": false,
      "lap_duration": 101.727,
      "segments_sector_1": [
        null,
        2048,
        2048,
        2048,
        2048,
        2049
      ],
      "segments_sector_2": [
        2048,
        2048,
        2048,
        2048,
        2048,
        2048,
        2048,
        2048
      ],
      "segments_sector_3": [
        2048,
        2048,
        2048,
        2048,
        2048,
        2064,
        2064,
        2064
      ],
      "st_speed": 303
    },
    {
      "meeting_key": 1271,
      "session_key": 9888,
      "driver_number": 4,
      "lap_number": 33,
      "date_start": "2025-10-19T19:58:05.640000+00:00",
      "duration_sector_1": 47.53,
      "duration_sector_2": 39.328,
      "duration_sector_3": 32.403,
      "i1_speed": 216,
      "i2_speed": 185,
      "is_pit_out_lap": true,
      "lap_duration": 119.261,
      "segments_sector_1": [
        2064,
        2064,
        2048,
        2048,
        2048,
        2048
      ],
      "segments_sector_2": [
        2048,
        2048,
        2048,
        2049,
        2049,
        2048,
        2048,
        2051
      ],
      "segments_sector_3": [
        2051,
        2049,
        2051,
        2048,
        2048,
        2048,
        2049,
        2049
      ],
      "st_speed": 300
    },
    {
      "meeting_key": 1271,
      "session_key": 9888,
      "driver_number": 4,
      "lap_number": 34,
      "date_start": "2025-10-19T20:00:04.916000+00:00",
      "duration_sector_1": 26.495,
      "duration_sector_2": 39.353,
      "duration_sector_3": 32.364,
      "i1_speed": 217,
      "i2_speed": 181,
      "is_pit_out_lap": false,
      "lap_duration": 98.212,
      "segments_sector_1": [
        2048,
        2048,
        2049,
        2049,
        2048,
        2048
      ],
      "segments_sector_2": [
        2048,
        2049,
        2048,
        2048,
        2048,
        2048,
        2048,
        2048
      ],
      "segments_sector_3": [
        2048,
        2048,
        2048,
        2048,
        2051,
        2051,
        2049,
        2049
      ],
      "st_speed": 305
    },
    {
      "meeting_key": 1271,
      "session_key": 9888,
      "driver_number": 4,
      "lap_number": 35,
      "date_start": "2025-10-19T20:01:43.080000+00:00",
      "duration_sector_1": 26.247,
      "duration_sector_2": 38.904,
      "duration_sector_3": 32.469,
      "i1_speed": 224,
      "i2_speed": 184,
      "is_pit_out_lap": false,
      "lap_duration": 97.62,
      "segments_sector_1": [
        null,
        2048,
        2049,
        2049,
        2048,
        2048
      ],
      "segments_sector_2": [
        2049,
        2049,
        2051,
        2049,
        2048,
        2048,
        2048,
        2048
      ],
      "segments_sector_3": [
        2048,
        2048,
        2048,
        2048,
        2048,
        2048,
        2048,
        2048
      ],
      "st_speed": 306
    },
    {
      "meeting_key": 1271,
      "session_key": 9888,
      "driver_number": 4,
      "lap_number": 36,
      "date_start": "2025-10-19T20:03:20.792000+00:00",
      "duration_sector_1": 26.351,
      "duration_sector_2": 39.124,
      "duration_sector_3": 32.832,
      "i1_speed": 221,
      "i2_speed": 184,
      "is_pit_out_lap": false,
      "lap_duration": 98.307,
      "segments_sector_1": [
        null,
        2048,
        2048,
        2048,
        2048,
        2048
      ],
      "segments_sector_2": [
        2048,
        2048,
        2048,
        2048,
        2048,
        2048,
        2048,
        2048
      ],
      "segments_sector_3": [
        2048,
        2048,
        2048,
        2048,
        2048,
        2048,
        2048,
        2048
      ],
      "st_speed": 307
    },
    {
      "meeting_key": 1271,
      "session_key": 9888,
      "driver_number": 4,
      "lap_number": 37,
      "date_start": "2025-10-19T20:04:59.067000+00:00",
      "duration_sector_1": 26.304,
      "duration_sector_2": 39.356,
      "duration_sector_3": 32.831,
      "i1_speed": 220,
      "i2_speed": 182,
      "is_pit_out_lap": false,
      "lap_duration": 98.491,
      "segments_sector_1": [
        null,
        2048,
        2048,
        2048,
        2048,
        2048
      ],
      "segments_sector_2": [
        2048,
        2048,
        2048,
        2048,
        2048,
        2048,
        2048,
        2048
      ],
      "segments_sector_3": [
        2048,
        2048,
        2048,
        2048,
        2048,
        2048,
        2048,
        2048
      ],
      "st_speed": 310
    },
    {
      "meeting_key": 1271,
      "session_key": 9888,
      "driver_number": 4,
      "lap_number": 38,
      "date_start": "2025-10-19T20:06:37.630000+00:00",
      "duration_sector_1": 25.882,
      "duration_sector_2": 39.204,
      "duration_sector_3": 33.071,
      "i1_speed": 225,
      "i2_speed": 184,
      "is_pit_out_lap": false,
      "lap_duration": 98.157,
      "segments_sector_1": [
        2049,
        2048,
        2048,
        2049,
        2049,
        2048
      ],
      "segments_sector_2": [
        2048,
        2048,
        2048,
        2048,
        2048,
        2048,
        2048,
        2048
      ],
      "segments_sector_3": [
        2048,
        2048,
        2048,
        2048,
        2048,
        2048,
        2048,
        2048
      ],
      "st_speed": 329
    },
    {
      "meeting_key": 1271,
      "session_key": 9888,
      "driver_number": 4,
      "lap_number": 39,
      "date_start": "2025-10-19T20:08:15.781000+00:00",
      "duration_sector_1": 26.313,
      "duration_sector_2": 39.386,
      "duration_sector_3": 32.805,
      "i1_speed": 226,
      "i2_speed": 184,
      "is_pit_out_lap": false,
      "lap_duration": 98.504,
      "segments_sector_1": [
        null,
        2049,
        2048,
        2049,
        2048,
        2048
      ],
      "segments_sector_2": [
        2048,
        2048,
        2048,
        2048,
        2048,
        2048,
        2048,
        2048
      ],
      "segments_sector_3": [
        2048,
        2048,
        2048,
        2048,
        2048,
        2048,
        2048,
        2048
      ],
      "st_speed": 329
    },
    {
      "meeting_key": 1271,
      "session_key": 9888,
      "driver_number": 4,
      "lap_number": 40,
      "date_start": "2025-10-19T20:09:54.202000+00:00",
      "duration_sector_1": 25.974,
      "duration_sector_2": 39.333,
      "duration_sector_3": 33.048,
      "i1_speed": 224,
      "i2_speed": 183,
      "is_pit_out_lap": false,
      "lap_duration": 98.355,
      "segments_sector_1": [
        null,
        2049,
        2048,
        2048,
        2048,
        2048
      ],
      "segments_sector_2": [
        2048,
        2048,
        2048,
        2048,
        2048,
        2048,
        2048,
        2048
      ],
      "segments_sector_3": [
        2048,
        2048,
        2048,
        2048,
        2048,
        2048,
        2048,
        2048
      ],
      "st_speed": 329
    },
    {
      "meeting_key": 1271,
      "session_key": 9888,
      "driver_number": 4,
      "lap_number": 41,
      "date_start": "2025-10-19T20:11:32.631000+00:00",
      "duration_sector_1": 25.971,
      "duration_sector_2": 39.304,
      "duration_sector_3": 33.577,
      "i1_speed": 225,
      "i2_speed": 182,
      "is_pit_out_lap": false,
      "lap_duration": 98.852,
      "segments_sector_1": [
        2048,
        2049,
        2048,
        2049,
        2048,
        2048
      ],
      "segments_sector_2": [
        2048,
        2048,
        2048,
        2048,
        2048,
        2048,
        2048,
        2048
      ],
      "segments_sector_3": [
        2048,
        2048,
        2048,
        2048,
        2048,
        2048,
        2048,
        2048
      ],
      "st_speed": 323
    },
    {
      "meeting_key": 1271,
      "session_key": 9888,
      "driver_number": 4,
      "lap_number": 42,
      "date_start": "2025-10-19T20:13:11.467000+00:00",
      "duration_sector_1": 26.646,
      "duration_sector_2": 39.715,
      "duration_sector_3": 33.424,
      "i1_speed": 216,
      "i2_speed": 181,
      "is_pit_out_lap": false,
      "lap_duration": 99.785,
      "segments_sector_1": [
        null,
        2048,
        2048,
        2048,
        2048,
        2048
      ],
      "segments_sector_2": [
        2048,
        2048,
        2048,
        2048,
        2048,
        2048,
        2048,
        2048
      ],
      "segments_sector_3": [
        2048,
        2048,
        2048,
        2048,
        2048,
        2048,
        2048,
        2048
      ],
      "st_speed": 308
    },
    {
      "meeting_key": 1271,
      "session_key": 9888,
      "driver_number": 4,
      "lap_number": 43,
      "date_start": "2025-10-19T20:14:51.196000+00:00",
      "duration_sector_1": 26.47,
      "duration_sector_2": 39.433,
      "duration_sector_3": 32.958,
      "i1_speed": 222,
      "i2_speed": 183,
      "is_pit_out_lap": false,
      "lap_duration": 98.861,
      "segments_sector_1": [
        null,
        2048,
        2048,
        2048,
        2048,
        2048
      ],
      "segments_sector_2": [
        2048,
        2048,
        2048,
        2048,
        2048,
        2048,
        2048,
        2048
      ],
      "segments_sector_3": [
        2048,
        2048,
        2048,
        2048,
        2048,
        2048,
        2048,
        2048
      ],
      "st_speed": 304
    },
    {
      "meeting_key": 1271,
      "session_key": 9888,
      "driver_number": 4,
      "lap_number": 44,
      "date_start": "2025-10-19T20:16:30.120000+00:00",
      "duration_sector_1": 26.271,
      "duration_sector_2": 39.44,
      "duration_sector_3": 33.066,
      "i1_speed": 228,
      "i2_speed": 185,
      "is_pit_out_lap": false,
      "lap_duration": 98.777,
      "segments_sector_1": [
        null,
        2048,
        2048,
        2048,
        2048,
        2048
      ],
      "segments_sector_2": [
        2049,
        2048,
        2048,
        2048,
        2048,
        2048,
        2048,
        2048
      ],
      "segments_sector_3": [
        2048,
        2048,
        2048,
        2048,
        2048,
        2048,
        2048,
        2048
      ],
      "st_speed": 307
    },
    {
      "meeting_key": 1271,
      "session_key": 9888,
      "driver_number": 4,
      "lap_number": 45,
      "date_start": "2025-10-19T20:18:08.854000+00:00",
      "duration_sector_1": 26.228,
      "duration_sector_2": 39.471,
      "duration_sector_3": 32.728,
      "i1_speed": 227,
      "i2_speed": 185,
      "is_pit_out_lap": false,
      "lap_duration": 98.427,
      "segments_sector_1": [
        null,
        2048,
        2048,
        2048,
        2048,
        2048
      ],
      "segments_sector_2": [
        2049,
        2048,
        2048,
        2048,
        2048,
        2048,
        2048,
        2048
      ],
      "segments_sector_3": [
        2048,
        2048,
        2048,
        2049,
        2048,
        2048,
        2048,
        2048
      ],
      "st_speed": 308
    },
    {
      "meeting_key": 1271,
      "session_key": 9888,
      "driver_number": 4,
      "lap_number": 46,
      "date_start": "2025-10-19T20:19:47.241000+00:00",
      "duration_sector_1": 26.058,
      "duration_sector_2": 39.429,
      "duration_sector_3": 32.659,
      "i1_speed": 233,
      "i2_speed": 184,
      "is_pit_out_lap": false,
      "lap_duration": 98.146,
      "segments_sector_1": [
        null,
        2048,
        2048,
        2048,
        2048,
        2049
      ],
      "segments_sector_2": [
        2048,
        2048,
        2048,
        2048,
        2048,
        2048,
        2048,
        2048
      ],
      "segments_sector_3": [
        2048,
        2048,
        2048,
        2051,
        2048,
        2048,
        2048,
        2048
      ],
      "st_speed": 308
    },
    {
      "meeting_key": 1271,
      "session_key": 9888,
      "driver_number": 4,
      "lap_number": 47,
      "date_start": "2025-10-19T20:21:25.437000+00:00",
      "duration_sector_1": 25.908,
      "duration_sector_2": 39.273,
      "duration_sector_3": 32.554,
      "i1_speed": 232,
      "i2_speed": 186,
      "is_pit_out_lap": false,
      "lap_duration": 97.735,
      "segments_sector_1": [
        null,
        2048,
        2048,
        2048,
        2049,
        2048
      ],
      "segments_sector_2": [
        2048,
        2048,
        2048,
        2048,
        2048,
        2048,
        2048,
        2048
      ],
      "segments_sector_3": [
        2048,
        2048,
        2048,
        2048,
        2048,
        2048,
        2048,
        2048
      ],
      "st_speed": 311
    },
    {
      "meeting_key": 1271,
      "session_key": 9888,
      "driver_number": 4,
      "lap_number": 48,
      "date_start": "2025-10-19T20:23:03.284000+00:00",
      "duration_sector_1": 25.945,
      "duration_sector_2": 39.267,
      "duration_sector_3": 32.657,
      "i1_speed": 230,
      "i2_speed": 185,
      "is_pit_out_lap": false,
      "lap_duration": 97.869,
      "segments_sector_1": [
        null,
        2048,
        2048,
        2049,
        2049,
        2049
      ],
      "segments_sector_2": [
        2048,
        2048,
        2048,
        2048,
        2048,
        2048,
        2048,
        2048
      ],
      "segments_sector_3": [
        2048,
        2048,
        2048,
        2051,
        2048,
        2048,
        2048,
        2048
      ],
      "st_speed": 310
    },
    {
      "meeting_key": 1271,
      "session_key": 9888,
      "driver_number": 4,
      "lap_number": 49,
      "date_start": "2025-10-19T20:24:40.990000+00:00",
      "duration_sector_1": 25.961,
      "duration_sector_2": 39.534,
      "duration_sector_3": 32.884,
      "i1_speed": 226,
      "i2_speed": 184,
      "is_pit_out_lap": false,
      "lap_duration": 98.379,
      "segments_sector_1": [
        null,
        2048,
        2048,
        2048,
        2048,
        2048
      ],
      "segments_sector_2": [
        2048,
        2048,
        2048,
        2048,
        2048,
        2048,
        2048,
        2048
      ],
      "segments_sector_3": [
        2048,
        2048,
        2048,
        2051,
        2048,
        2048,
        2048,
        2048
      ],
      "st_speed": 308
    },
    {
      "meeting_key": 1271,
      "session_key": 9888,
      "driver_number": 4,
      "lap_number": 50,
      "date_start": "2025-10-19T20:26:19.478000+00:00",
      "duration_sector_1": 25.832,
      "duration_sector_2": 39.429,
      "duration_sector_3": 33.234,
      "i1_speed": 218,
      "i2_speed": 184,
      "is_pit_out_lap": false,
      "lap_duration": 98.495,
      "segments_sector_1": [
        null,
        2049,
        2048,
        2049,
        2048,
        2048
      ],
      "segments_sector_2": [
        2048,
        2048,
        2048,
        2048,
        2048,
        2048,
        2048,
        2048
      ],
      "segments_sector_3": [
        2048,
        2048,
        2048,
        2048,
        2048,
        2048,
        2048,
        2048
      ],
      "st_speed": 331
    },
    {
      "meeting_key": 1271,
      "session_key": 9888,
      "driver_number": 4,
      "lap_number": 51,
      "date_start": "2025-10-19T20:27:57.933000+00:00",
      "duration_sector_1": 26.3,
      "duration_sector_2": 39.634,
      "duration_sector_3": 33.184,
      "i1_speed": 223,
      "i2_speed": 185,
      "is_pit_out_lap": false,
      "lap_duration": 99.118,
      "segments_sector_1": [
        2049,
        2049,
        2048,
        2048,
        2048,
        2048
      ],
      "segments_sector_2": [
        2048,
        2048,
        2048,
        2048,
        2049,
        2051,
        2049,
        2048
      ],
      "segments_sector_3": [
        2048,
        2048,
        2048,
        2048,
        2048,
        2048,
        2048,
        2048
      ],
      "st_speed": 334
    },
    {
      "meeting_key": 1271,
      "session_key": 9888,
      "driver_number": 4,
      "lap_number": 52,
      "date_start": "2025-10-19T20:29:36.972000+00:00",
      "duration_sector_1": 25.989,
      "duration_sector_2": 39.373,
      "duration_sector_3": 32.465,
      "i1_speed": 234,
      "i2_speed": 185,
      "is_pit_out_lap": false,
      "lap_duration": 97.827,
      "segments_sector_1": [
        2048,
        2048,
        2048,
        2049,
        2048,
        2049
      ],
      "segments_sector_2": [
        2049,
        2048,
        2048,
        2048,
        2048,
        2048,
        2048,
        2048
      ],
      "segments_sector_3": [
        2048,
        2048,
        2048,
        2048,
        2049,
        2048,
        2048,
        2048
      ],
      "st_speed": 299
    },
    {
      "meeting_key": 1271,
      "session_key": 9888,
      "driver_number": 4,
      "lap_number": 53,
      "date_start": "2025-10-19T20:31:14.833000+00:00",
      "duration_sector_1": 26.041,
      "duration_sector_2": 39.377,
      "duration_sector_3": 32.702,
      "i1_speed": 227,
      "i2_speed": 185,
      "is_pit_out_lap": false,
      "lap_duration": 98.12,
      "segments_sector_1": [
        null,
        2048,
        2048,
        2048,
        2048,
        2048
      ],
      "segments_sector_2": [
        2048,
        2048,
        2048,
        2048,
        2048,
        2048,
        2048,
        2048
      ],
      "segments_sector_3": [
        2048,
        2048,
        2048,
        2048,
        2048,
        2048,
        2048,
        2048
      ],
      "st_speed": 306
    },
    {
      "meeting_key": 1271,
      "session_key": 9888,
      "driver_number": 4,
      "lap_number": 54,
      "date_start": "2025-10-19T20:32:53.048000+00:00",
      "duration_sector_1": 25.991,
      "duration_sector_2": 39.325,
      "duration_sector_3": 32.849,
      "i1_speed": 231,
      "i2_speed": 186,
      "is_pit_out_lap": false,
      "lap_duration": 98.165,
      "segments_sector_1": [
        null,
        2048,
        2048,
        2048,
        2049,
        2048
      ],
      "segments_sector_2": [
        2049,
        2048,
        2048,
        2048,
        2048,
        2048,
        2048,
        2048
      ],
      "segments_sector_3": [
        2048,
        2048,
        2048,
        2048,
        2048,
        2048,
        2048,
        2048
      ],
      "st_speed": 307
    },
    {
      "meeting_key": 1271,
      "session_key": 9888,
      "driver_number": 4,
      "lap_number": 55,
      "date_start": "2025-10-19T20:34:31.163000+00:00",
      "duration_sector_1": 26.181,
      "duration_sector_2": 39.398,
      "duration_sector_3": 32.668,
      "i1_speed": null,
      "i2_speed": 186,
      "is_pit_out_lap": false,
      "lap_duration": 98.247,
      "segments_sector_1": [
        null,
        2048,
        2048,
        2048,
        2048,
        2048
      ],
      "segments_sector_2": [
        2049,
        2048,
        2048,
        2048,
        2048,
        2048,
        2048,
        2048
      ],
      "segments_sector_3": [
        2048,
        2048,
        2048,
        2048,
        2048,
        2048,
        2048,
        2048
      ],
      "st_speed": 304
    },
    {
      "meeting_key": 1271,
      "session_key": 9888,
      "driver_number": 4,
      "lap_number": 56,
      "date_start": "2025-10-19T20:36:09.392000+00:00",
      "duration_sector_1": 26.144,
      "duration_sector_2": 39.589,
      "duration_sector_3": 33.318,
      "i1_speed": null,
      "i2_speed": 186,
      "is_pit_out_lap": false,
      "lap_duration": 99.051,
      "segments_sector_1": [
        null,
        2048,
        2048,
        2048,
        2048,
        2048
      ],
      "segments_sector_2": [
        2048,
        2048,
        2048,
        2048,
        2048,
        2048,
        2048,
        2048
      ],
      "segments_sector_3": [
        2048,
        2048,
        2048,
        2048,
        2048,
        2048,
        2048,
        2048
      ],
      "st_speed": 305
    }
  ],
  "stints": [
    {
      "meeting_key": 1271,
      "session_key": 9888,
      "stint_number": 1,
      "driver_number": 4,
      "lap_start": 1,
      "lap_end": 32,
      "compound": "MEDIUM",
      "tyre_age_at_start": 0
    },
    {
      "meeting_key": 1271,
      "session_key": 9888,
      "stint_number": 2,
      "driver_number": 4,
      "lap_start": 33,
      "lap_end": 56,
      "compound": "SOFT",
      "tyre_age_at_start": 6
    }
  ],
  "pit": [
    {
      "date": "2025-10-19T19:58:29.191000+00:00",
      "session_key": 9888,
      "meeting_key": 1271,
      "driver_number": 4,
      "pit_duration": 24.5,
      "lap_number": 32
    }
  ]
}