{
  "laps": [
    {
      "meeting_key": 1267,
      "session_key": 9920,
      "driver_number": 44,
      "lap_number": 1,
      "date_start": null,
      "duration_sector_1": null,
      "duration_sector_2": 27.712,
      "duration_sector_3": 23.269,
      "i1_speed": 281,
      "i2_speed": 265,
      "is_pit_out_lap": false,
      "lap_duration": null,
      "segments_sector_1": [
        null,
        2049,
        2049,
        2049,
        2049,
        2049,
        2049,
        2049
      ],
      "segments_sector_2": [
        2049,
        2049,
        2049,
        2049,
        2049,
        2049,
        2049,
        2049
      ],
      "segments_sector_3": [
        2049,
        2049,
        2049,
        2049,
        2049,
        2049,
        2049,
        2049
      ],
      "st_speed": 227
    },
    {
      "meeting_key": 1267,
      "session_key": 9920,
      "driver_number": 44,
      "lap_number": 2,
      "date_start": "2025-08-31T13:04:44.433000+00:00",
      "duration_sector_1": 26.405,
      "duration_sector_2": 27.548,
      "duration_sector_3": 22.763,
      "i1_speed": 284,
      "i2_speed": 275,
      "is_pit_out_lap": false,
      "lap_duration": 76.716,
      "segments_sector_1": [
        2049,
        2049,
        2049,
        2049,
        2049,
        2049,
        2049,
        2048
      ],
      "segments_sector_2": [
        2049,
        2049,
        2049,
        2049,
        2048,
        2049,
        2049,
        2048
      ],
      "segments_sector_3": [
        2049,
        2048,
        2049,
        2049,
        2049,
        2049,
        2049,
        2049
      ],
      "st_speed": 290
    },
    {
      "meeting_key": 1267,
      "session_key": 9920,
      "driver_number": 44,
      "lap_number": 3,
      "date_start": "2025-08-31T13:06:01.268000+00:00",
      "duration_sector_1": 26.112,
      "duration_sector_2": 27.692,
      "duration_sector_3": 22.645,
      "i1_speed": 287,
      "i2_speed": 278,
      "is_pit_out_lap": false,
      "lap_duration": 76.449,
      "segments_sector_1": [
        null,
        2049,
        2049,
        2049,
        2048,
        2048,
        2049,
        2049
      ],
      "segments_sector_2": [
        2049,
        2048,
        2048,
        2048,
        2048,
        2048,
        2049,
        2049
      ],
      "segments_sector_3": [
        2049,
        2049,
        2049,
        2049,
        2049,
        2049,
        2049,
        2049
      ],
      "st_speed": 305
    },
    {
      "meeting_key": 1267,
      "session_key": 9920,
      "driver_number": 44,
      "lap_number": 4,
      "date_start": "2025-08-31T13:07:17.751000+00:00",
      "duration_sector_1": 26.331,
      "duration_sector_2": 27.56,
      "duration_sector_3": 22.679,
      "i1_speed": 285,
      "i2_speed": 276,
      "is_pit_out_lap": false,
      "lap_duration": 76.57,
      "segments_sector_1": [
        2048,
        2048,
        2048,
        2048,
        2048,
        2049,
        2048,
        2048
      ],
      "segments_sector_2": [
        2048,
        2048,
        2048,
        2048,
        2049,
        2049,
        2048,
        2048
      ],
      "segments_sector_3": [
        2049,
        2049,
        2048,
        2048,
        2048,
        2048,
        2048,
        2049
      ],
      "st_speed": 294
    },
    {
      "meeting_key": 1267,
      "session_key": 9920,
      "driver_number": 44,
      "lap_number": 5,
      "date_start": "2025-08-31T13:08:34.231000+00:00",
      "duration_sector_1": 26.2,
      "duration_sector_2": 27.394,
      "duration_sector_3": 22.838,
      "i1_speed": null,
      "i2_speed": 278,
      "is_pit_out_lap": false,
      "lap_duration": 76.432,
      "segments_sector_1": [
        null,
        2048,
        2048,
        2048,
        2048,
        2048,
        2049,
        2048
      ],
      "segments_sector_2": [
        2048,
        2049,
        2048,
        2048,
        2048,
        2048,
        2048,
        2049
      ],
      "segments_sector_3": [
        2048,
        2048,
        2048,
        2049,
        2048,
        2048,
        2048,
        2048
      ],
      "st_speed": 291
    },
    {
      "meeting_key": 1267,
      "session_key": 9920,
      "driver_number": 44,
      "lap_number": 6,
      "date_start": "2025-08-31T13:09:50.642000+00:00",
      "duration_sector_1": 25.949,
      "duration_sector_2": 27.151,
      "duration_sector_3": 22.584,
      "i1_speed": 284,
      "i2_speed": 277,
      "is_pit_out_lap": false,
      "lap_duration": 75.684,
      "segments_sector_1": [
        null,
        2048,
        2049,
        2048,
        2049,
        2049,
        2049,
        2048
      ],
      "segments_sector_2": [
        2048,
        2049,
        2048,
        2049,
        2048,
        2049,
        2048,
        2048
      ],
      "segments_sector_3": [
        2048,
        2048,
        2048,
        2049,
        2049,
        2049,
        2049,
        2048
      ],
      "st_speed": null
    },
    {
      "meeting_key": 1267,
      "session_key": 9920,
      "driver_number": 44,
      "lap_number": 7,
      "date_start": "2025-08-31T13:11:06.431000+00:00",
      "duration_sector_1": 25.946,
      "duration_sector_2": 27.467,
      "duration_sector_3": 22.623,
      "i1_speed": 285,
      "i2_speed": 275,
      "is_pit_out_lap": false,
      "lap_duration": 76.036,
      "segments_sector_1": [
        null,
        2048,
        2048,
        2048,
        2048,
        2048,
        2048,
        2048
      ],
      "segments_sector_2": [
        2048,
        2048,
        2049,
        2048,
        2048,
        2048,
        2048,
        2048
      ],
      "segments_sector_3": [
        2049,
        2049,
        2048,
        2048,
        2048,
        2048,
        2048,
        2048
      ],
      "st_speed": 303
    },
    {
      "meeting_key": 1267,
      "session_key": 9920,
      "driver_number": 44,
      "lap_number": 8,
      "date_start": "2025-08-31T13:12:22.352000+00:00",
      "duration_sector_1": 25.826,
      "duration_sector_2": 27.457,
      "duration_sector_3": 22.679,
      "i1_speed": null,
      "i2_speed": 276,
      "is_pit_out_lap": false,
      "lap_duration": 75.962,
      "segments_sector_1": [
        null,
        2048,
        2048,
        2048,
        2049,
        2049,
        2049,
        2048
      ],
      "segments_sector_2": [
        2048,
        2049,
        2048,
        2048,
        2048,
        2049,
        2048,
        2048
      ],
      "segments_sector_3": [
        2048,
        2048,
        2048,
        2048,
        2048,
        2048,
        2048,
        2048
      ],
      "st_speed": 300
    },
    {
      "meeting_key": 1267,
      "session_key": 9920,
      "driver_number": 44,
      "lap_number": 9,
      "date_start": "2025-08-31T13:13:38.367000+00:00",
      "duration_sector_1": 25.855,
      "duration_sector_2": 27.24,
      "duration_sector_3": 22.761,
      "i1_speed": 284,
      "i2_speed": 275,
      "is_pit_out_lap": false,
      "lap_duration": 75.856,
      "segments_sector_1": [
        null,
        2048,
        2048,
        2048,
        2049,
        2048,
        2048,
        2048
      ],
      "segments_sector_2": [
        2048,
        2049,
        2049,
        2048,
        2048,
        2048,
        2048,
        2048
      ],
      "segments_sector_3": [
        2048,
        2048,
        2048,
        2049,
        2048,
        2048,
        2048,
        2048
      ],
      "st_speed": 305
    },
    {
      "meeting_key": 1267,
      "session_key": 9920,
      "driver_number": 44,
      "lap_number": 10,
      "date_start": "2025-08-31T13:14:54.215000+00:00",
      "duration_sector_1": 25.95,
      "duration_sector_2": 27.421,
      "duration_sector_3": 22.743,
      "i1_speed": 285,
      "i2_speed": 275,
      "is_pit_out_lap": false,
      "lap_duration": 76.114,
      "segments_sector_1": [
        null,
        2048,
        2048,
        2048,
        2048,
        2048,
        2048,
        2048
      ],
      "segments_sector_2": [
        2048,
        2048,
        2048,
        2048,
        2048,
        2048,
        2048,
        2048
      ],
      "segments_sector_3": [
        2048,
        2048,
        2048,
        2048,
        2048,
        2048,
        2048,
        2048
      ],
      "st_speed": 295
    },
    {
      "meeting_key": 1267,
      "session_key": 9920,
      "driver_number": 44,
      "lap_number": 11,
      "date_start": "2025-08-31T13:16:10.389000+00:00",
      "duration_sector_1": 26.071,
      "duration_sector_2": 27.54,
      "duration_sector_3": 22.947,
      "i1_speed": 283,
      "i2_speed": 274,
      "is_pit_out_lap": false,
      "lap_duration": 76.558,
      "segments_sector_1": [
        null,
        2048,
        2048,
        2048,
        2048,
        2048,
        2048,
        2048
      ],
      "segments_sector_2": [
        2048,
        2048,
        2048,
        2048,
        2048,
        2048,
        2048,
        2048
      ],
      "segments_sector_3": [
        2048,
        2048,
        2048,
        2048,
        2048,
        2048,
        2048,
        2048
      ],
      "st_speed": 298
    },
    {
      "meeting_key": 1267,
      "session_key": 9920,
      "driver_number": 44,
      "lap_number": 12,
      "date_start": "2025-08-31T13:17:26.962000+00:00",
      "duration_sector_1": 25.917,
      "duration_sector_2": 27.44,
      "duration_sector_3": 22.814,
      "i1_speed": 285,
      "i2_speed": 275,
      "is_pit_out_lap": false,
      "lap_duration": 76.171,
      "segments_sector_1": [
        null,
        2048,
        2048,
        2048,
        2048,
        2048,
        2049,
        2048
      ],
      "segments_sector_2": [
        2048,
        2049,
        2048,
        2048,
        2048,
        2048,
        2048,
        2048
      ],
      "segments_sector_3": [
        2049,
        2048,
        2048,
        2048,
        2048,
        2048,
        2048,
        2048
      ],
      "st_speed": 297
    },
    {
      "meeting_key": 1267,
      "session_key": 9920,
      "driver_number": 44,
      "lap_number": 13,
      "date_start": "2025-08-31T13:18:43.081000+00:00",
      "duration_sector_1": 25.817,
      "duration_sector_2": 27.566,
      "duration_sector_3": 23.097,
      "i1_speed": null,
      "i2_speed": 274,
      "is_pit_out_lap": false,
      "lap_duration": 76.48,
      "segments_sector_1": [
        null,
        2049,
        2048,
        2048,
        2049,
        2048,
        2048,
        2048
      ],
      "segments_sector_2": [
        2048,
        2048,
        2048,
        2048,
        2048,
        2048,
        2048,
        2048
      ],
      "segments_sector_3": [
        2048,
        2048,
        2048,
        2048,
        2048,
        2048,
        2048,
        2048
      ],
      "st_speed": 310
    },
    {
      "meeting_key": 1267,
      "session_key": 9920,
      "driver_number": 44,
      "lap_number": 14,
      "date_start": "2025-08-31T13:19:59.585000+00:00",
      "duration_sector_1": 25.978,
      "duration_sector_2": 27.577,
      "duration_sector_3": 23.029,
      "i1_speed": null,
      "i2_speed": 266,
      "is_pit_out_lap": false,
      "lap_duration": 76.584,
      "segments_sector_1": [
        null,
        2048,
        2048,
        2048,
        2048,
        2048,
        2049,
        2048
      ],
      "segments_sector_2": [
        2048,
        2049,
        2048,
        2048,
        2048,
        2048,
        2048,
        2048
      ],
      "segments_sector_3": [
        2048,
        2048,
        2048,
        2049,
        2048,
        2048,
        2048,
        2048
      ],
      "st_speed": 291
    },
    {
      "meeting_key": 1267,
      "session_key": 9920,
      "driver_number": 44,
      "lap_number": 15,
      "date_start": "2025-08-31T13:21:16.174000+00:00",
      "duration_sector_1": 25.851,
      "duration_sector_2": 27.537,
      "duration_sector_3": 22.983,
      "i1_speed": null,
      "i2_speed": 265,
      "is_pit_out_lap": false,
      "lap_duration": 76.371,
      "segments_sector_1": [
        null,
        2048,
        2048,
        2048,
        2049,
        2049,
        2048,
        2049
      ],
      "segments_sector_2": [
        2048,
        2049,
        2048,
        2048,
        2048,
        2048,
        2048,
        2048
      ],
      "segments_sector_3": [
        2048,
        2048,
        2048,
        2048,
        2048,
        2048,
        2048,
        2048
      ],
      "st_speed": 298
    },
    {
      "meeting_key": 1267,
      "session_key": 9920,
      "driver_number": 44,
      "lap_number": 16,
      "date_start": "2025-08-31T13:22:32.429000+00:00",
      "duration_sector_1": 25.795,
      "duration_sector_2": 27.358,
      "duration_sector_3": 22.972,
      "i1_speed": null,
      "i2_speed": 265,
      "is_pit_out_lap": false,
      "lap_duration": 76.125,
      "segments_sector_1": [
        null,
        2048,
        2048,
        2048,
        2049,
        2048,
        2048,
        2048
      ],
      "segments_sector_2": [
        2048,
        2049,
        2049,
        2048,
        2048,
        2048,
        2048,
        2048
      ],
      "segments_sector_3": [
        2048,
        2048,
        2048,
        2048,
        2048,
        2048,
        2048,
        2048
      ],
      "st_speed": 300
    },
    {
      "meeting_key": 1267,
      "session_key": 9920,
      "driver_number": 44,
      "lap_number": 17,
      "date_start": "2025-08-31T13:23:48.645000+00:00",
      "duration_sector_1": 25.87,
      "duration_sector_2": 27.371,
      "duration_sector_3": 22.938,
      "i1_speed": 284,
      "i2_speed": 265,
      "is_pit_out_lap": false,
      "lap_duration": 76.179,
      "segments_sector_1": [
        null,
        2048,
        2048,
        2048,
        2049,
        2048,
        2048,
        2048
      ],
      "segments_sector_2": [
        2048,
        2048,
        2048,
        2048,
        2048,
        2048,
        2048,
        2048
      ],
      "segments_sector_3": [
        2048,
        2048,
        2048,
        2049,
        2048,
        2048,
        2048,
        2048
      ],
      "st_speed": 297
    },
    {
      "meeting_key": 1267,
      "session_key": 9920,
      "driver_number": 44,
      "lap_number": 18,
      "date_start": "2025-08-31T13:25:04.916000+00:00",
      "duration_sector_1": 25.716,
      "duration_sector_2": 27.559,
      "duration_sector_3": 22.753,
      "i1_speed": 286,
      "i2_speed": 274,
      "is_pit_out_lap": false,
      "lap_duration": 76.028,
      "segments_sector_1": [
        null,
        2049,
        2048,
        2048,
        2048,
        2049,
        2049,
        2049
      ],
      "segments_sector_2": [
        2048,
        2048,
        2048,
        2048,
        2048,
        2048,
        2048,
        2048
      ],
      "segments_sector_3": [
        2048,
        2048,
        2048,
        2048,
        2048,
        2048,
        2048,
        2048
      ],
      "st_speed": 299
    },
    {
      "meeting_key": 1267,
      "session_key": 9920,
      "driver_number": 44,
      "lap_number": 19,
      "date_start": "2025-08-31T13:26:20.908000+00:00",
      "duration_sector_1": 25.706,
      "duration_sector_2": 27.698,
      "duration_sector_3": 22.767,
      "i1_speed": 287,
      "i2_speed": 275,
      "is_pit_out_lap": false,
      "lap_duration": 76.171,
      "segments_sector_1": [
        null,
        2049,
        2048,
        2048,
        2048,
        2048,
        2049,
        2049
      ],
      "segments_sector_2": [
        2049,
        2048,
        2048,
        2048,
        2048,
        2048,
        2048,
        2048
      ],
      "segments_sector_3": [
        2048,
        2048,
        2048,
        2048,
        2048,
        2048,
        2048,
        2048
      ],
      "st_speed": 313
    },
    {
      "meeting_key": 1267,
      "session_key": 9920,
      "driver_number": 44,
      "lap_number": 20,
      "date_start": "2025-08-31T13:27:37.051000+00:00",
      "duration_sector_1": 25.935,
      "duration_sector_2": 27.753,
      "duration_sector_3": 22.873,
      "i1_speed": null,
      "i2_speed": 273,
      "is_pit_out_lap": false,
      "lap_duration": 76.561,
      "segments_sector_1": [
        null,
        2048,
        2048,
        2048,
        2048,
        2048,
        2048,
        2048
      ],
      "segments_sector_2": [
        2049,
        2048,
        2048,
        2048,
        2048,
        2048,
        2048,
        2048
      ],
      "segments_sector_3": [
        2048,
        2048,
        2048,
        2048,
        2048,
        2048,
        2048,
        2048
      ],
      "st_speed": 308
    },
    {
      "meeting_key": 1267,
      "session_key": 9920,
      "driver_number": 44,
      "lap_number": 21,
      "date_start": "2025-08-31T13:28:53.519000+00:00",
      "duration_sector_1": 25.767,
      "duration_sector_2": 27.811,
      "duration_sector_3": 22.89,
      "i1_speed": null,
      "i2_speed": 275,
      "is_pit_out_lap": false,
      "lap_duration": 76.468,
      "segments_sector_1": [
        null,
        2048,
        2048,
        2048,
        2048,
        2048,
        2048,
        2048
      ],
      "segments_sector_2": [
        2048,
        2048,
        2048,
        2048,
        2048,
        2048,
        2048,
        2048
      ],
      "segments_sector_3": [
        2048,
        2048,
        2048,
        2048,
        2048,
        2048,
        2048,
        2048
      ],
      "st_speed": 305
    },
    {
      "meeting_key": 1267,
      "session_key": 9920,
      "driver_number": 44,
      "lap_number": 22,
      "date_start": "2025-08-31T13:30:10.069000+00:00",
      "duration_sector_1": 25.959,
      "duration_sector_2": 27.903,
      "duration_sector_3": 23.064,
      "i1_speed": null,
      "i2_speed": 273,
      "is_pit_out_lap": false,
      "lap_duration": 76.926,
      "segments_sector_1": [
        null,
        2048,
        2048,
        2048,
        2048,
        2048,
        2048,
        2048
      ],
      "segments_sector_2": [
        2048,
        2048,
        2048,
        2048,
        2048,
        2048,
        2048,
        2048
      ],
      "segments_sector_3": [
        2049,
        2048,
        2048,
        2048,
        2048,
        2048,
        2048,
        2048
      ],
      "st_speed": 308
    },
    {
      "meeting_key": 1267,
      "session_key": 9920,
      "driver_number": 44,
      "lap_number": 23,
      "date_start": "2025-08-31T13:31:26.885000+00:00",
      "duration_sector_1": null,
      "duration_sector_2": null,
      "duration_sector_3": null,
      "i1_speed": null,
      "i2_speed": null,
      "is_pit_out_lap": false,
      "lap_duration": null,
      "segments_sector_1": [
        null,
        0,
        0,
        0,
        0,
        0,
        0,
        0
      ],
      "segments_sector_2": null,
      "segments_sector_3": null,
      "st_speed": 302
    }
  ],
  "stints": [
    {
      "meeting_key": 1267,
      "session_key": 9920,
      "stint_number": 1,
      "driver_number": 44,
      "lap_start": 1,
      "lap_end": 22,
      "compound": "MEDIUM",
      "tyre_age_at_start": 0
    }
  ],
  "pit": []
}